kpol/__init__.py
kpol/arithmetic/__init__.py
kpol/arithmetic/add.py
kpol/arithmetic/mult.py
kpol/comm/__init__.py
kpol/comm/eyediagram.py
kpol-0.3.3.dist-info/LICENSE
kpol-0.3.3.dist-info/METADATA
kpol-0.3.3.dist-info/WHEEL
kpol-0.3.3.dist-info/top_level.txt
kpol-0.3.3.dist-info/RECORD
